urelativedelta/__init__.py
urelativedelta/daterule.py
urelativedelta/relativedelta.py
urelativedelta/utils.py
urelativedelta-0.4.0.dist-info/METADATA
urelativedelta-0.4.0.dist-info/WHEEL
urelativedelta-0.4.0.dist-info/licenses/LICENSE
urelativedelta-0.4.0.dist-info/RECORD
