Metadata-Version: 2.1
Name: urelativedelta
Version: 0.4.0
Summary: A small fast implementation of relativedelta
Project-URL: Homepage, https://github.com/olliemath/urelativedelta
Project-URL: Bug Tracker, https://github.com/olliemath/urelativedelta
Project-URL: Repository, https://github.com/olliemath/urelativedelta
Author-email: Oliver Margetts <oliver.margetts@gmail.com>
License-File: LICENSE
Keywords: date,daterule,datetime,dateutil,monthly,relativedelta,rrule,timedelta
Classifier: License :: OSI Approved :: MIT License
Classifier: Operating System :: OS Independent
Classifier: Programming Language :: Python :: 3
Requires-Python: >=3.9
